<?xml version="1.0" encoding="UTF-8"?>
<?xml-stylesheet type='text/xsl' href='/xml/xsd2html2xml/xsd2html2xml.xsl'?>

<recipe
    xmlns="https://cazzscookingcommunity.github.io"
    xmlns:xsi="http://www.w3.org/2001/XMLSchema-instance" 
    xsi:schemaLocation="https://cazzscookingcommunity.github.io /xml/recipe.xsd"> 
    
<title>Callums Chilli</title>
<filename>callums_chilli.xml</filename>
<thumbnail>../images/callums_chilli.jpeg</thumbnail>
<category>Dinner</category>
<diet>Vegan</diet>
<ingredient>3 cans chopped tomatoes </ingredient>
<ingredient>2 cans kidney beans</ingredient>
<ingredient>2 cans black beans</ingredient>
<ingredient>1 can corn</ingredient>
<ingredient>3 sweet potatoes peeled and chopped </ingredient>
<ingredient>2-3 TBsp olive oil</ingredient>
<ingredient>2-4 garlic cloves crushed </ingredient>
<ingredient>2 teaspoon cumin </ingredient>
<ingredient>1/2 teaspoon coriander and chilli </ingredient>
<ingredient>salt and pepper to taste</ingredient>
<ingredient>Colourful peppers for garnish (if desired)</ingredient>
<step>
Heat oil in large pot and cook garlic for a few minutes. Add spices and cook for another minute or two. Add sweet potatoes and stir to coat. Add chopped tomatoes and cook until sweet potatoes cooked, but not mushy (about 10-20 minutes.) Rinse and drain all cans and add to pot.  Add salt and pepper if using. Taste and add additional spices if necessary.  Serve with any or all of grated cheese, guacamole, salsa, sour cream, chopped peppers, grated carrots, shredded lettuce, corn chips and flat bread.
    </step>
</recipe>

